{
  "DataFolder": ".\\Podcasts",
  "MaxItemsPerFeed": 1,
  "Feeds": [
    {
      "Url": "http://feeds.tsf.pt/semmoderacao",
      "Downloaded": [
        "sem_20170712.mp3"
      ]
    },
    {
      "Url": "http://feeds.tsf.pt/Tsf-GovernoSombra-Podcast",
      "Downloaded": [
        "gov_20170716.mp3"
      ]
    },
    {
      "Url": "http://feeds.tsf.pt/Tsf-HistoriasJustica",
      "Downloaded": [
        "his_20170630.mp3"
      ]
    },
    {
      "Url": "http://feeds.tsf.pt/politicapura",
      "Downloaded": [
        "pol_20170713.mp3"
      ]
    },
    {
      "Url": "http://feeds.tsf.pt/Tsf-ReportagemTsf",
      "Downloaded": [
        "rep_20170706.mp3"
      ]
    },
    {
      "Url": "http://feeds.tsf.pt/Tsf-BlocoCentral",
      "Downloaded": [
        "blo_20170714.mp3"
      ]
    },
    {
      "Url": "http://feeds.wnyc.org/radiolab",
      "Downloaded": [
        "radiolab_podcast17truthwarriors.mp3"
      ]
    },
    {
      "Url": "http://www.rtp.pt/play/itunes/2086",
      "Downloaded": [
        "SNPCOLNIADEGATOSLX_4795306-1707191533.mp3"
      ]
    },
    {
      "Url": "http://www.rtp.pt/play/itunes/283",
      "Downloaded": [
        "ContraditrioWEB027_4808340-1707281454.mp3"
      ]
    },
    {
      "Url": "http://www.rtp.pt/play/itunes/309",
      "Downloaded": [
        "GrandeReportagem010_4795364-1707191706.mp3"
      ]
    },
    {
      "Url": "http://www.rtp.pt/play/itunes/280",
      "Downloaded": [
        "MariaFlorPedroso025_4796435-1707201034.mp3"
      ]
    },
    {
      "Url": "http://www.rtp.pt/play/itunes/280",
      "Downloaded": [
        "MariaFlorPedroso025_4796435-1707201034.mp3"
      ]
    },
    {
      "Url": "http://www.rtp.pt/play/itunes/2955",
      "Downloaded": [
        "AMosca16328Julwav_4799369-1707211710.mp3"
      ]
    },
    {
      "Url": "http://www.rtp.pt/play/itunes/1830",
      "Downloaded": [
        "RadioTaxismo145_4796612-1707201128.mp3"
      ]
    },
    {
      "Url": "http://www.rtp.pt/play/itunes/282",
      "Downloaded": [
        "VG23JULFINAL_4800149-1707230123.mp3"
      ]
    },
    {
      "Url": "http://www.rtp.pt/play/itunes/2057",
      "Downloaded": [
        "ofiodameada_4807767-1707280957.mp3"
      ]
    },
    {
      "Url": "http://www.rtp.pt/play/itunes/293",
      "Downloaded": [
        "Portugalex148_4801892-1707241804.mp3"
      ]
    },
    {
      "Url": "http://www.rtp.pt/play/itunes/2054",
      "Downloaded": [
        "ConversaCapital029_4808579-1707281848.mp3"
      ]
    },
    {
      "Url": "http://www.rtp.pt/play/itunes/2311",
      "Downloaded": [
        "AnatomiadoCrimePodcast40_4445330-1612161515.mp3"
      ]
    },
    {
      "Url": "http://feeds.feedburner.com/rc-programadamanha",
      "Downloaded": [
        "RC_MANHA_07-07-2017.mp3"
      ]
    },
    {
      "Url": "http://podcasts.files.bbci.co.uk/b00jkr1q.rss",
      "Download": [
      ]
    },
    {
      "Url": "http://feeds.feedburner.com/CorbettReportRSS",
      "Downloads": [
      ]
    }
  ]
}